pormalizer/__init__.py
pormalizer/pormalizer.py
pormalizer-0.1.0.dist-info/LICENSE
pormalizer-0.1.0.dist-info/METADATA
pormalizer-0.1.0.dist-info/WHEEL
pormalizer-0.1.0.dist-info/top_level.txt
pormalizer-0.1.0.dist-info/RECORD
