Metadata-Version: 2.1
Name: pormalizer
Version: 0.1.0
Summary: Persian normalizer for text processing
Home-page: https://github.com/xurvan/pormalizer
Author: Xurvan
License: apache-2.0
Download-URL: https://github.com/xurvan/pormalizer/archive/v0.1.0.zip
Project-URL: Code, https://github.com/xurvan/pormalizer
Project-URL: Issue tracker, https://github.com/xurvan/pormalizer/issues
Platform: UNKNOWN
Classifier: Development Status :: 3 - Alpha
Classifier: Intended Audience :: Developers
Classifier: Topic :: Software Development
Classifier: License :: OSI Approved :: Apache Software License
Classifier: Programming Language :: Python :: 3
Requires-Python: >=3.6
License-File: LICENSE
